seapi
