Metadata-Version: 1.1
Name: seapi
Version: 0.1.5.dev1
Summary: a python library to query SiliconExpert API to gain information about electronic components and manufacturers/suppliers
Home-page: https://github.com/biwa7636/seapi
Author: Gayatri Ghanakota, Richard Rymer, Bin Wang
Author-email: binwang.cu@gmail.com
License: MIT
Keywords: api siliconexpert components
Platform: UNKNOWN
Classifier: Development Status :: 3 - Alpha
Classifier: Intended Audience :: Developers
Classifier: License :: OSI Approved :: MIT License
Classifier: Programming Language :: Python :: 2.6
Classifier: Programming Language :: Python :: 2.7
